bottle_autodocs/__init__.py
bottle_autodocs/bottle_autodocs.py
bottle_autodocs-0.1.24.dist-info/LICENSE
bottle_autodocs-0.1.24.dist-info/METADATA
bottle_autodocs-0.1.24.dist-info/WHEEL
bottle_autodocs-0.1.24.dist-info/top_level.txt
bottle_autodocs-0.1.24.dist-info/RECORD
